arduino_hid_controller/__init__.py
arduino_hid_controller/arduino_controller.py
arduino_hid_controller/constants.py
arduino_hid_controller/hid_controller.py
arduino_hid_controller/keyboard_controller.py
arduino_hid_controller/mouse_controller.py
arduino_hid_controller-3.0.0.dist-info/METADATA
arduino_hid_controller-3.0.0.dist-info/WHEEL
arduino_hid_controller-3.0.0.dist-info/top_level.txt
arduino_hid_controller-3.0.0.dist-info/RECORD
