Metadata-Version: 2.1
Name: arduino-hid-controller
Version: 3.0.0
Summary: Python library to control Arduino as HID (Keyboard/Mouse) via Serial
Home-page: https://github.com/duelist-dev/arduino-hid-controller
Author: Duelist
Author-email: duelist.dev@gmail.com
Project-URL: Source, https://github.com/duelist-dev/arduino-hid-controller
Keywords: arduino,hid,keyboard,mouse,automation,serial
Classifier: Programming Language :: Python :: 3
Classifier: License :: OSI Approved :: MIT License
Classifier: Operating System :: OS Independent
Classifier: Topic :: Home Automation
Classifier: Topic :: System :: Hardware
Requires-Python: >=3.7
Requires-Dist: pyserial>=3.5
Requires-Dist: pynput>=1.7.6
Requires-Dist: pyautogui>=0.9.53
Provides-Extra: dev
Requires-Dist: twine>=4.0.2; extra == "dev"
Requires-Dist: wheel>=0.38.4; extra == "dev"
